veriCAS/__init__.py
veriCAS/atom_eco.py
veriCAS/test.py
veriCAS-0.0.1001.dist-info/LICENSE
veriCAS-0.0.1001.dist-info/METADATA
veriCAS-0.0.1001.dist-info/WHEEL
veriCAS-0.0.1001.dist-info/top_level.txt
veriCAS-0.0.1001.dist-info/RECORD
