Metadata-Version: 2.1
Name: veriCAS
Version: 0.0.1001
Summary: Calculate atom economy for chemical reactions using reaction SMILES
Author-email: Samuele Giani <samuele.giani@empa.ch>
Project-URL: Homepage, https://pypi.org/project/veriCAS/
Project-URL: Issues, https://pypi.org/project/veriCAS/
Classifier: Programming Language :: Python :: 3
Classifier: License :: OSI Approved :: GNU General Public License v3 (GPLv3)
Classifier: Operating System :: OS Independent
Requires-Python: >=3.8
License-File: LICENSE
